deltw/__init__.py
deltw/cleaner.py
deltw/cli.py
deltw/util.py
deltw-2.1.0.dist-info/LICENSE
deltw-2.1.0.dist-info/METADATA
deltw-2.1.0.dist-info/WHEEL
deltw-2.1.0.dist-info/entry_points.txt
deltw-2.1.0.dist-info/top_level.txt
deltw-2.1.0.dist-info/RECORD
