Metadata-Version: 2.1
Name: deltw
Version: 2.1.0
Summary: Twitter Cleaner to delete archived tweets
Home-page: https://github.com/dceoy/deltw
Author: Daichi Narushima
Author-email: dnarsil+github@gmail.com
Classifier: Development Status :: 4 - Beta
Classifier: Environment :: Console
Classifier: Intended Audience :: Developers
Classifier: License :: OSI Approved :: MIT License
Classifier: Operating System :: POSIX :: Linux
Classifier: Operating System :: MacOS
Classifier: Programming Language :: Python :: 3
Classifier: Topic :: Internet
Requires-Python: >=3.5
License-File: LICENSE
Requires-Dist: requests-oauthlib
Requires-Dist: pyyaml
